setup.py
HubbardMeanField.egg-info/PKG-INFO
HubbardMeanField.egg-info/SOURCES.txt
HubbardMeanField.egg-info/dependency_links.txt
HubbardMeanField.egg-info/top_level.txt
hubbardmeanfield/__init__.py
hubbardmeanfield/test_substrate.py
hubbardmeanfield/tests.py
hubbardmeanfield/hubbard/__init__.py
hubbardmeanfield/hubbard/base.py
hubbardmeanfield/hubbard/kagome.py
hubbardmeanfield/hubbard/misc.py
hubbardmeanfield/hubbard/progress.py
hubbardmeanfield/hubbard/utils.py
hubbardmeanfield/hubbard/kpoints/__init__.py
hubbardmeanfield/hubbard/kpoints/base.py
hubbardmeanfield/hubbard/kpoints/kagome.py