Metadata-Version: 2.1
Name: HubbardMeanField
Version: 1.0
Summary: mean field method for hubbard model
Home-page: http://www.issp.cas.cn/
Author: LTF.123
Author-email: tfliu@mail.ustc.edu.cn
License: UNKNOWN
Platform: UNKNOWN
Classifier: Programming Language :: Python :: 3
Classifier: License :: OSI Approved :: MIT License
Classifier: Operating System :: OS Independent
